docugenr8_svg/__init__.py
docugenr8_svg/css_style.py
docugenr8_svg/global_styles.py
docugenr8_svg/selector_functions.py
docugenr8_svg/specificity.py
docugenr8_svg/svg.py
docugenr8_svg/svg_attr.py
docugenr8_svg/svg_element.py
docugenr8_svg-0.0.1.dist-info/LICENSE
docugenr8_svg-0.0.1.dist-info/METADATA
docugenr8_svg-0.0.1.dist-info/WHEEL
docugenr8_svg-0.0.1.dist-info/top_level.txt
docugenr8_svg-0.0.1.dist-info/RECORD
